sndict/__init__.py
sndict/app.py
sndict/exceptions.py
sndict/nesteddict.py
sndict/shared.py
sndict/structurednesteddict.py
sndict/utils.py
sndict-0.1.2.dist-info/METADATA
sndict-0.1.2.dist-info/RECORD
sndict-0.1.2.dist-info/WHEEL
sndict-0.1.2.dist-info/entry_points.txt
sndict-0.1.2.dist-info/top_level.txt
