Metadata-Version: 2.1
Name: sndict
Version: 0.1.2
Summary: Nested Extensions to Python dictionaries
Home-page: https://github.com/zphang/sndict
Author: Jason Phang
Author-email: email@jasonphang.com
License: MIT license
Keywords: sndict
Platform: UNKNOWN
Classifier: Development Status :: 2 - Pre-Alpha
Classifier: Intended Audience :: Developers
Classifier: License :: OSI Approved :: MIT License
Classifier: Natural Language :: English
Classifier: Programming Language :: Python :: 3
Classifier: Programming Language :: Python :: 3.5
Classifier: Programming Language :: Python :: 3.6
